llmbatch/__init__.py
llmbatch/cli.py
llmbatch/models/__init__.py
llmbatch/models/schemas.py
llmbatch/pipelines/__init__.py
llmbatch/pipelines/inference.py
llmbatch/pipelines/post.py
llmbatch/pipelines/pre.py
llmbatch/services/__init__.py
llmbatch/services/openai_service.py
llmbatch/utils/__init__.py
llmbatch/utils/general.py
llmbatch/utils/images.py
llmbatch/utils/messages.py
llm_batch-0.1.8.dist-info/METADATA
llm_batch-0.1.8.dist-info/WHEEL
llm_batch-0.1.8.dist-info/entry_points.txt
llm_batch-0.1.8.dist-info/licenses/LICENSE
llm_batch-0.1.8.dist-info/RECORD
