Metadata-Version: 2.4
Name: llm-batch
Version: 0.1.8
Summary: Batch CLI tool for running batch inference with local LLMs
Project-URL: Homepage, https://github.com/mmysior/llm-batch
Project-URL: Issues, https://github.com/mmysior/llm-batch/issues
Author: Marek Piotr Mysior
License-File: LICENSE
Requires-Python: >=3.12
Requires-Dist: anthropic>=0.50.0
Requires-Dist: click>=8.1.8
Requires-Dist: instructor>=1.7.9
Requires-Dist: openai>=1.76.0
Requires-Dist: pillow>=11.2.1
Requires-Dist: python-dotenv>=1.1.0
Requires-Dist: pyyaml>=6.0.2
